{
    "eventos": [
        {
            "evento": "Entrada en la dinamica",
            "fecha": "2/2/2016",
            "hora": "17:40:13:720"
        },
        {
            "evento": "Opcion correcta",
            "fecha": "2/2/2016",
            "hora": "17:40:23:242"
        },
        {
            "evento": "Salida de la dinamica ",
            "fecha": "2/2/2016",
            "infoAdicional": "Superada",
            "hora": "17:40:32:863"
        }
    ],
    "dinamica": "DinamicaGalletas"
}